popular
popular/providers
