Metadata-Version: 1.1
Name: popular
Version: 0.1.1
Summary: Minimalist social auth package.
Home-page: https://github.com/ryannjohnson/popular-python
Author: Ryan N Johnson
Author-email: ryan@ryannjohnson.com
License: MIT License
Platform: UNKNOWN
Classifier: Development Status :: 3 - Alpha
Classifier: Intended Audience :: Developers
Classifier: License :: OSI Approved :: MIT License
Classifier: Programming Language :: Python :: 3
